{
  "$schema": "https://developer.microsoft.com/json-schemas/fabric/item/report/definition/visualContainer/2.10.0/schema.json",
  "name": "dd278cde47074c9571ea",
  "position": {
    "x": 206.20060790273558,
    "y": 66.139817629179333,
    "z": 3,
    "height": 117.68996960486322,
    "width": 181.88449848024317,
    "tabOrder": 3
  },
  "visual": {
    "visualType": "pivotTable",
    "query": {
      "queryState": {
        "Rows": {
          "projections": [
            {
              "field": {
                "Column": {
                  "Expression": {
                    "SourceRef": {
                      "Entity": "mart_ev"
                    }
                  },
                  "Property": "connectype"
                }
              },
              "queryRef": "mart_ev.connectype",
              "nativeQueryRef": "connectype",
              "active": true
            }
          ]
        },
        "Values": {
          "projections": [
            {
              "field": {
                "Measure": {
                  "Expression": {
                    "SourceRef": {
                      "Entity": "mart_ev"
                    }
                  },
                  "Property": "Chargers"
                }
              },
              "queryRef": "mart_ev.Chargers",
              "nativeQueryRef": "Chargers"
            }
          ]
        }
      }
    },
    "objects": {
      "values": [
        {
          "properties": {
            "backColor": {
              "solid": {
                "color": {
                  "expr": {
                    "FillRule": {
                      "Input": {
                        "Measure": {
                          "Expression": {
                            "SourceRef": {
                              "Entity": "mart_ev"
                            }
                          },
                          "Property": "Chargers"
                        }
                      },
                      "FillRule": {
                        "linearGradient2": {
                          "min": {
                            "color": {
                              "Literal": {
                                "Value": "'minColor'"
                              }
                            }
                          },
                          "max": {
                            "color": {
                              "Literal": {
                                "Value": "'maxColor'"
                              }
                            }
                          },
                          "nullColoringStrategy": {
                            "strategy": {
                              "Literal": {
                                "Value": "'asZero'"
                              }
                            }
                          }
                        }
                      }
                    }
                  }
                }
              }
            }
          },
          "selector": {
            "data": [
              {
                "dataViewWildcard": {
                  "matchingOption": 1
                }
              }
            ],
            "metadata": "mart_ev.Chargers"
          }
        }
      ]
    },
    "drillFilterOtherVisuals": true
  },
  "filterConfig": {
    "filters": [
      {
        "name": "fd89d80e4694d8805073",
        "field": {
          "Column": {
            "Expression": {
              "SourceRef": {
                "Entity": "mart_ev"
              }
            },
            "Property": "connectype"
          }
        },
        "type": "Categorical"
      },
      {
        "name": "23388734a9cded006b67",
        "field": {
          "Measure": {
            "Expression": {
              "SourceRef": {
                "Entity": "mart_ev"
              }
            },
            "Property": "Chargers"
          }
        },
        "type": "Advanced"
      }
    ]
  }
}